glib_log_bridge/__init__.py
glib_log_bridge/glib2python.py
glib_log_bridge/python2glib.py
tests/__init__.py
tests/test_glib2python.py
tests/test_python2glib.py
glib_log_bridge-0.0.1.dist-info/LICENSE
glib_log_bridge-0.0.1.dist-info/METADATA
glib_log_bridge-0.0.1.dist-info/WHEEL
glib_log_bridge-0.0.1.dist-info/top_level.txt
glib_log_bridge-0.0.1.dist-info/RECORD
