Metadata-Version: 2.1
Name: glib-log-bridge
Version: 0.0.1
Summary: Bridge Python and GLib logging facilities
Home-page: https://github.com/Neui/python-glib-log-bridge
Author: Neui
License: UNKNOWN
Platform: UNKNOWN
Classifier: Programming Language :: Python :: 3
Classifier: License :: OSI Approved :: MIT License
Classifier: Operating System :: OS Independent
Classifier: Development Status :: 2 - Pre-Alpha
Classifier: Intended Audience :: Developers
Classifier: Topic :: Software Development :: Libraries
Classifier: Topic :: System :: Logging
Classifier: Typing :: Typed
Requires-Python: >=3.5
